odoo/addons/stock_picking_completion_info/README.rst
odoo/addons/stock_picking_completion_info/__init__.py
odoo/addons/stock_picking_completion_info/__manifest__.py
odoo/addons/stock_picking_completion_info/i18n/es_AR.po
odoo/addons/stock_picking_completion_info/i18n/it.po
odoo/addons/stock_picking_completion_info/i18n/stock_picking_completion_info.pot
odoo/addons/stock_picking_completion_info/models/__init__.py
odoo/addons/stock_picking_completion_info/models/stock_picking.py
odoo/addons/stock_picking_completion_info/readme/CONTRIBUTORS.rst
odoo/addons/stock_picking_completion_info/readme/DESCRIPTION.rst
odoo/addons/stock_picking_completion_info/static/description/icon.png
odoo/addons/stock_picking_completion_info/static/description/index.html
odoo/addons/stock_picking_completion_info/tests/__init__.py
odoo/addons/stock_picking_completion_info/tests/test_stock_picking_completion_info.py
odoo/addons/stock_picking_completion_info/views/stock_picking.xml
odoo14_addon_stock_picking_completion_info-14.0.1.1.1.dev5.dist-info/METADATA
odoo14_addon_stock_picking_completion_info-14.0.1.1.1.dev5.dist-info/WHEEL
odoo14_addon_stock_picking_completion_info-14.0.1.1.1.dev5.dist-info/top_level.txt
odoo14_addon_stock_picking_completion_info-14.0.1.1.1.dev5.dist-info/RECORD
