Metadata-Version: 2.1
Name: odoo14-addon-stock_picking_completion_info
Version: 14.0.1.1.1.dev5
Summary: Display on current document completion information according to next operations
Home-page: https://github.com/OCA/wms
Author: Camptocamp, Odoo Community Association (OCA)
Author-email: support@odoo-community.org
License: AGPL-3
Classifier: Programming Language :: Python
Classifier: Framework :: Odoo
Classifier: Framework :: Odoo :: 14.0
Classifier: License :: OSI Approved :: GNU Affero General Public License v3
Classifier: Development Status :: 4 - Beta
Requires-Python: >=3.6
Requires-Dist: odoo14-addon-stock-move-common-dest
Requires-Dist: odoo <14.1dev,>=14.0a
